{"ApprovalTime": "2017-03-24T00:19:16Z", "AutoApprovalTime": "2017-03-24T00:19:03Z", "AssignmentId": "3I7DHKZYGN00JF02JB9C1NP6JRMF5K", "WorkerId": "anon4", "answers": {"data": {"reactionTimeArray": [63337, 99411, 140123, 167433, 189107, 214229, 236721, 257601, 280661, 302530, 323245, 342650, 380611, 403446, 439034, 459351, 479466, 495936, 513291, 531579], "browserVersion": 56, "valence": [4, 4, 2, 3, 7, 4, 3, 4, 2, 6, 2, 2, 5, 4, 5, 5, 4, 4, 4, 5], "arousal": [3, 3, 2, 2, 6, 3, 3, 2, 2, 5, 2, 2, 5, 1, 4, 5, 2, 2, 2, 2], "discrete": [3, 3, 2, 5, 1, 3, 2, 3, 3, 1, 2, 3, 1, 3, 1, 1, 2, 3, 3, 3], "gender": "F", "clear": [6, 2, 6, 6, 7, 5, 6, 6, 6, 7, 7, 1, 6, 4, 6, 6, 2, 5, 2, 6], "orderArray": ["994622", "985731", "1184386", "1124426", "1264786", "1216775", "1213807", "1209748", "1130376", "1208215", "992348", "1238789", "1167641", "1249012", "1100347", "1209675", "1120963", "1083796", "1137107", "1077907"], "raceother": "", "browserOS": "Windows", "nativeLanguage": "english", "intensity": [5, 4, 4, 3, 6, 4, 3, 4, 5, 5, 3, 4, 3, 4, 5, 5, 4, 4, 4, 4], "race": "white", "comments": "", "startTime": 1490313827321, "need": [2, 3, 1, 2, 1, 2, 2, 2, 2, 2, 3, 2, 4, 2, 3, 2, 4, 2, 2, 3], "endTime": 1490314358900, "age": "43", "browser": "Chrome"}}, "AcceptTime": "2017-03-23T23:37:02Z", "HITId": "3TKSOBLOHLG98U72PG9SWZ2P0KNBB1", "Assignment": "", "AssignmentStatus": "Approved", "SubmitTime": "2017-03-24T00:14:03Z"}