{"ApprovalTime": "2017-03-23T22:51:16Z", "AutoApprovalTime": "2017-03-23T22:50:41Z", "AssignmentId": "3OSWBBLG1EXCNE6GYBXH56D50DCDXD", "WorkerId": "anon5", "answers": {"data": {"reactionTimeArray": [43721, 75851, 97054, 125591, 154245, 180842, 398107, 418814, 441689, 569416, 584772, 600348, 619095, 641282, 656208, 942541, 956503, 971963, 995049, 1007775], "browserVersion": 51, "valence": [6, 4, 4, 4, 4, 4, 5, 4, 4, 5, 4, 4, 4, 5, 5, 5, 4, 4, 5, 4], "arousal": [3, 2, 1, 2, 1, 1, 4, 1, 1, 3, 1, 1, 2, 2, 2, 3, 1, 1, 3, 1], "discrete": [1, 3, 3, 3, 3, 3, 1, 3, 3, 1, 3, 2, 3, 1, 1, 1, 3, 3, 1, 3], "gender": "M", "clear": [6, 4, 5, 6, 6, 2, 6, 1, 6, 5, 7, 5, 6, 7, 5, 6, 7, 5, 7, 6], "orderArray": ["1149713", "1234350", "1199071", "1073670", "1114840", "1113569", "1084502", "1248347", "1109092", "1069244", "1186682", "1067125", "1230242", "1143240", "1206827", "1258827", "1241975", "1193750", "1241336", "1258046"], "raceother": "", "browserOS": "Windows", "nativeLanguage": "english", "intensity": [3, 1, 1, 2, 1, 1, 4, 1, 1, 2, 1, 1, 2, 2, 2, 2, 1, 1, 3, 1], "race": "white", "comments": "", "startTime": 1490307958270, "need": [3, 4, 5, 2, 2, 3, 1, 1, 2, 1, 1, 1, 1, 1, 1, 1, 2, 1, 1, 1], "endTime": 1490308966045, "age": "37", "browser": "Firefox"}}, "AcceptTime": "2017-03-23T22:28:19Z", "HITId": "3TD33TP5DL24PK2AJ29W1OIJI22BA6", "Assignment": "", "AssignmentStatus": "Approved", "SubmitTime": "2017-03-23T22:45:41Z"}