{"ApprovalTime": "2017-03-23T22:41:16Z", "AutoApprovalTime": "2017-03-23T22:41:04Z", "AssignmentId": "36AHBNMV1RC1NJWQ37JJOKKE2J6DYJ", "WorkerId": "anon1", "answers": {"data": {"reactionTimeArray": [22530, 40475, 78506, 126155, 143379, 156741, 166848, 182929, 197179, 214375, 224980, 261861, 304816, 315814, 328633, 384829, 400144, 413049, 427987, 439067], "browserVersion": 56, "valence": [4, 3, 2, 4, 3, 5, 4, 5, 4, 5, 4, 4, 5, 6, 4, 4, 4, 4, 3, 4], "arousal": [1, 2, 3, 3, 2, 2, 2, 2, 1, 4, 2, 3, 2, 2, 2, 2, 2, 1, 1, 2], "discrete": [3, 2, 2, 3, 2, 3, 3, 1, 3, 1, 3, 3, 1, 1, 3, 3, 3, 3, 3, 3], "gender": "M", "clear": [6, 2, 5, 3, 5, 5, 3, 6, 1, 5, 4, 2, 5, 6, 4, 4, 7, 7, 1, 7], "orderArray": ["1245137", "1144865", "1085431", "1237064", "1022272", "1230596", "1187007", "1054972", "1218992", "1176414", "975950", "1204669", "943980", "1167863", "1074816", "1070730", "987783", "1236739", "1254200", "866345"], "raceother": "", "browserOS": "Windows", "nativeLanguage": "english", "intensity": [1, 1, 2, 2, 2, 2, 1, 1, 1, 2, 2, 1, 2, 5, 1, 1, 1, 1, 1, 1], "race": "white", "comments": "", "startTime": 1490308101010, "need": [2, 5, 4, 3, 2, 4, 3, 2, 1, 2, 3, 2, 2, 3, 3, 2, 2, 2, 1, 2], "endTime": 1490308540077, "age": "35", "browser": "Chrome"}}, "AcceptTime": "2017-03-23T22:28:10Z", "HITId": "3VI0PC2ZAYK04RZCYH6WRGTGQMUOXR", "Assignment": "", "AssignmentStatus": "Approved", "SubmitTime": "2017-03-23T22:36:04Z"}